agave/__init__.py
agave/version.py
agave/chalice/__init__.py
agave/chalice/rest_api.py
agave/chalice/models/__init__.py
agave/chalice/models/helpers.py
agave/core/__init__.py
agave/core/exc.py
agave/core/filters.py
agave/core/loggers.py
agave/core/blueprints/__init__.py
agave/core/blueprints/decorators.py
agave/fastapi/__init__.py
agave/fastapi/rest_api.py
agave/fastapi/middlewares/__init__.py
agave/fastapi/middlewares/error_handlers.py
agave/fastapi/middlewares/loggin_route.py
agave/tasks/__init__.py
agave/tasks/sqs_celery_client.py
agave/tasks/sqs_client.py
agave/tasks/sqs_tasks.py
tests/__init__.py
tests/conftest.py
tests/blueprint/__init__.py
tests/blueprint/test_blueprint.py
tests/chalice/__init__.py
tests/chalice/test_imports.py
tests/chalice/models/__init__.py
tests/chalice/models/test_uuid_field_account.py
tests/core/__init__.py
tests/core/test_decorators.py
tests/core/test_filters.py
tests/core/test_loggers.py
tests/fastapi/__init__.py
tests/fastapi/test_app.py
tests/fastapi/test_imports.py
tests/fastapi/test_loggin_route.py
tests/tasks/__init__.py
tests/tasks/conftest.py
tests/tasks/test_imports.py
tests/tasks/test_sqs_celery_client.py
tests/tasks/test_sqs_client.py
tests/tasks/test_sqs_tasks.py
agave-1.1.0.dist-info/LICENSE
agave-1.1.0.dist-info/METADATA
agave-1.1.0.dist-info/WHEEL
agave-1.1.0.dist-info/top_level.txt
agave-1.1.0.dist-info/RECORD
