Metadata-Version: 2.2
Name: agave
Version: 1.1.0
Summary: Rest_api
Home-page: https://github.com/cuenca-mx/agave
Author: Cuenca
Author-email: dev@cuenca.com
Classifier: Programming Language :: Python :: 3.9
Classifier: Programming Language :: Python :: 3.10
Classifier: Programming Language :: Python :: 3.11
Classifier: Programming Language :: Python :: 3.12
Classifier: Programming Language :: Python :: 3.13
Classifier: License :: OSI Approved :: MIT License
Classifier: Operating System :: OS Independent
Requires-Python: >=3.9
License-File: LICENSE
Requires-Dist: cuenca-validations<3.0.0,>=2.1.0
Requires-Dist: mongoengine<0.30.0,>=0.29.0
Requires-Dist: mongoengine-plus<2.0.0,>=1.0.0
Requires-Dist: python-multipart<0.0.30,>=0.0.20
Provides-Extra: chalice
Requires-Dist: chalice<2.0.0,>=1.30.0; extra == "chalice"
Provides-Extra: fastapi
Requires-Dist: fastapi<1.0.0,>=0.115.0; extra == "fastapi"
Requires-Dist: starlette-context<0.4.0,>=0.3.2; extra == "fastapi"
Provides-Extra: tasks
Requires-Dist: aiobotocore<3.0.0,>=2.0.0; extra == "tasks"
Requires-Dist: types-aiobotocore-sqs<3.0.0,>=2.1.0; extra == "tasks"
Dynamic: author
Dynamic: author-email
Dynamic: classifier
Dynamic: description
Dynamic: description-content-type
Dynamic: home-page
Dynamic: provides-extra
Dynamic: requires-dist
Dynamic: requires-python
Dynamic: summary
